Flask_LazyViews-0.6.dist-info/WHEEL
Flask_LazyViews-0.6.dist-info/DESCRIPTION.rst
Flask_LazyViews-0.6.dist-info/metadata.json
Flask_LazyViews-0.6.dist-info/METADATA
Flask_LazyViews-0.6.dist-info/RECORD
Flask_LazyViews-0.6.dist-info/top_level.txt
flask_lazyviews/utils.py
flask_lazyviews/__init__.py
flask_lazyviews/lazyviews.py
