Metadata-Version: 1.1
Name: Flask-LazyViews
Version: 0.6
Summary: Registers URL routes for Flask application or blueprint in lazy way.
Home-page: https://github.com/playpauseandstop/Flask-LazyViews
Author: Igor Davydenko
Author-email: playpauseandstop@gmail.com
License: BSD License
Keywords: flask lazy views
Platform: any
Classifier: Development Status :: 5 - Production/Stable
Classifier: Environment :: Web Environment
Classifier: Operating System :: OS Independent
Classifier: Topic :: Utilities
Classifier: Programming Language :: Python :: 2
Classifier: Programming Language :: Python :: 2.6
Classifier: Programming Language :: Python :: 2.7
Classifier: Programming Language :: Python :: 3
Classifier: Programming Language :: Python :: 3.3
Classifier: Programming Language :: Python :: 3.4
Classifier: Programming Language :: Python :: Implementation :: PyPy
Classifier: Topic :: Internet :: WWW/HTTP :: Dynamic Content
Classifier: Topic :: Software Development :: Libraries :: Python Modules
Classifier: License :: OSI Approved :: BSD License
